pytree/__init__.py
pytree/__main__.py
pytree/pytree.py
swrs_pytree-1.0.5.dist-info/LICENSE
swrs_pytree-1.0.5.dist-info/METADATA
swrs_pytree-1.0.5.dist-info/WHEEL
swrs_pytree-1.0.5.dist-info/entry_points.txt
swrs_pytree-1.0.5.dist-info/top_level.txt
swrs_pytree-1.0.5.dist-info/RECORD
