Metadata-Version: 2.1
Name: swrs-pytree
Version: 1.0.5
Summary: A tree implementation for Python
Author-email: Sawors <sawors@proton.me>
Project-URL: Homepage, https://github.com/Sawors/pytree
Project-URL: Issues, https://github.com/Sawors/pytree/issues
Classifier: Programming Language :: Python :: 3
Classifier: Operating System :: OS Independent
Classifier: Intended Audience :: Developers
Classifier: License :: OSI Approved :: Apache Software License
Requires-Python: >=3.8
License-File: LICENSE
Requires-Dist: natsort >=8.4.0
